<annotation>
	<folder>Short</folder>
	<filename>11_short_06.jpg</filename>
	<path>/home/weapon/Desktop/PCB_DATASET/Short/11_short_06.jpg</path>
	<source>
		<database>Unknown</database>
	</source>
	<size>
		<width>2282</width>
		<height>2248</height>
		<depth>3</depth>
	</size>
	<segmented>0</segmented>
	<object>
		<name>short</name>
		<pose>Unspecified</pose>
		<truncated>0</truncated>
		<difficult>0</difficult>
		<bndbox>
			<xmin>887</xmin>
			<ymin>1167</ymin>
			<xmax>951</xmax>
			<ymax>1245</ymax>
		</bndbox>
	</object>
	<object>
		<name>short</name>
		<pose>Unspecified</pose>
		<truncated>0</truncated>
		<difficult>0</difficult>
		<bndbox>
			<xmin>1158</xmin>
			<ymin>1158</ymin>
			<xmax>1222</xmax>
			<ymax>1239</ymax>
		</bndbox>
	</object>
	<object>
		<name>short</name>
		<pose>Unspecified</pose>
		<truncated>0</truncated>
		<difficult>0</difficult>
		<bndbox>
			<xmin>822</xmin>
			<ymin>1934</ymin>
			<xmax>893</xmax>
			<ymax>2013</ymax>
		</bndbox>
	</object>
	<object>
		<name>short</name>
		<pose>Unspecified</pose>
		<truncated>0</truncated>
		<difficult>0</difficult>
		<bndbox>
			<xmin>1834</xmin>
			<ymin>1822</ymin>
			<xmax>1935</xmax>
			<ymax>1886</ymax>
		</bndbox>
	</object>
	<object>
		<name>short</name>
		<pose>Unspecified</pose>
		<truncated>0</truncated>
		<difficult>0</difficult>
		<bndbox>
			<xmin>1045</xmin>
			<ymin>1345</ymin>
			<xmax>1124</xmax>
			<ymax>1417</ymax>
		</bndbox>
	</object>
</annotation>
