<annotation>
	<folder>Missing_hole</folder>
	<filename>10_missing_hole_01.jpg</filename>
	<path>/home/weapon/Desktop/PCB_DATASET/Missing_hole/10_missing_hole_01.jpg</path>
	<source>
		<database>Unknown</database>
	</source>
	<size>
		<width>2240</width>
		<height>2016</height>
		<depth>3</depth>
	</size>
	<segmented>0</segmented>
	<object>
		<name>missing_hole</name>
		<pose>Unspecified</pose>
		<truncated>0</truncated>
		<difficult>0</difficult>
		<bndbox>
			<xmin>1346</xmin>
			<ymin>677</ymin>
			<xmax>1479</xmax>
			<ymax>789</ymax>
		</bndbox>
	</object>
	<object>
		<name>missing_hole</name>
		<pose>Unspecified</pose>
		<truncated>0</truncated>
		<difficult>0</difficult>
		<bndbox>
			<xmin>1907</xmin>
			<ymin>490</ymin>
			<xmax>1982</xmax>
			<ymax>571</ymax>
		</bndbox>
	</object>
	<object>
		<name>missing_hole</name>
		<pose>Unspecified</pose>
		<truncated>0</truncated>
		<difficult>0</difficult>
		<bndbox>
			<xmin>1963</xmin>
			<ymin>651</ymin>
			<xmax>2053</xmax>
			<ymax>727</ymax>
		</bndbox>
	</object>
	<object>
		<name>missing_hole</name>
		<pose>Unspecified</pose>
		<truncated>0</truncated>
		<difficult>0</difficult>
		<bndbox>
			<xmin>1794</xmin>
			<ymin>1144</ymin>
			<xmax>1891</xmax>
			<ymax>1234</ymax>
		</bndbox>
	</object>
	<object>
		<name>missing_hole</name>
		<pose>Unspecified</pose>
		<truncated>0</truncated>
		<difficult>0</difficult>
		<bndbox>
			<xmin>1017</xmin>
			<ymin>1270</ymin>
			<xmax>1111</xmax>
			<ymax>1350</ymax>
		</bndbox>
	</object>
</annotation>
