<annotation>
	<folder>Missing_hole</folder>
	<filename>11_missing_hole_09.jpg</filename>
	<path>/home/weapon/Desktop/PCB_DATASET/Missing_hole/11_missing_hole_09.jpg</path>
	<source>
		<database>Unknown</database>
	</source>
	<size>
		<width>2282</width>
		<height>2248</height>
		<depth>3</depth>
	</size>
	<segmented>0</segmented>
	<object>
		<name>missing_hole</name>
		<pose>Unspecified</pose>
		<truncated>0</truncated>
		<difficult>0</difficult>
		<bndbox>
			<xmin>857</xmin>
			<ymin>224</ymin>
			<xmax>937</xmax>
			<ymax>313</ymax>
		</bndbox>
	</object>
	<object>
		<name>missing_hole</name>
		<pose>Unspecified</pose>
		<truncated>0</truncated>
		<difficult>0</difficult>
		<bndbox>
			<xmin>912</xmin>
			<ymin>593</ymin>
			<xmax>983</xmax>
			<ymax>673</ymax>
		</bndbox>
	</object>
	<object>
		<name>missing_hole</name>
		<pose>Unspecified</pose>
		<truncated>0</truncated>
		<difficult>0</difficult>
		<bndbox>
			<xmin>1548</xmin>
			<ymin>552</ymin>
			<xmax>1637</xmax>
			<ymax>637</ymax>
		</bndbox>
	</object>
	<object>
		<name>missing_hole</name>
		<pose>Unspecified</pose>
		<truncated>0</truncated>
		<difficult>0</difficult>
		<bndbox>
			<xmin>712</xmin>
			<ymin>1265</ymin>
			<xmax>793</xmax>
			<ymax>1350</ymax>
		</bndbox>
	</object>
	<object>
		<name>missing_hole</name>
		<pose>Unspecified</pose>
		<truncated>0</truncated>
		<difficult>0</difficult>
		<bndbox>
			<xmin>1302</xmin>
			<ymin>1749</ymin>
			<xmax>1389</xmax>
			<ymax>1834</ymax>
		</bndbox>
	</object>
</annotation>
